aiookru/__init__.py
aiookru/api.py
aiookru/auth.py
aiookru/session.py
aiookru-1.0.0.dist-info/LICENSE
aiookru-1.0.0.dist-info/METADATA
aiookru-1.0.0.dist-info/WHEEL
aiookru-1.0.0.dist-info/top_level.txt
aiookru-1.0.0.dist-info/RECORD
