Metadata-Version: 2.1
Name: aiookru
Version: 1.0.0
Summary: Python ok.ru API wrapper
Home-page: https://github.com/konstantintogoi/aiookru
Download-URL: https://pypi.org/project/aiookru/
Author: Konstantin Togoi
Author-email: konstantin.togoi@gmail.com
License: BSD
Project-URL: Documentation, https://konstantintogoi.github.io/aiookru
Keywords: ok.ru rest api asyncio
Platform: Any
Classifier: Development Status :: 5 - Production/Stable
Classifier: Environment :: Web Environment
Classifier: Framework :: AsyncIO
Classifier: Intended Audience :: Developers
Classifier: License :: OSI Approved :: BSD License
Classifier: Operating System :: OS Independent
Classifier: Programming Language :: Python
Classifier: Programming Language :: Python :: 3.7
Classifier: Programming Language :: Python :: 3.8
Classifier: Programming Language :: Python :: 3.9
Classifier: Programming Language :: Python :: 3 :: Only
Classifier: Topic :: Internet
Classifier: Topic :: Internet :: WWW/HTTP
Classifier: Topic :: Software Development :: Libraries :: Python Modules
Requires-Python: >=3.7
License-File: LICENSE
Requires-Dist: httpx
